portainer_deploy_tool/__init__.py
portainer_deploy_tool/__main__.py
portainer_deploy_tool/create_or_update_stack.py
portainer_deploy_tool/update_service_by_webhook.py
portainer_deploy_tool/update_service_in_stack.py
portainer_deploy_tool/utils.py
portainer_deploy_tool-0.0.5.dist-info/LICENSE
portainer_deploy_tool-0.0.5.dist-info/METADATA
portainer_deploy_tool-0.0.5.dist-info/WHEEL
portainer_deploy_tool-0.0.5.dist-info/entry_points.txt
portainer_deploy_tool-0.0.5.dist-info/top_level.txt
portainer_deploy_tool-0.0.5.dist-info/RECORD
