Metadata-Version: 2.1
Name: portainer-deploy-tool
Version: 0.0.5
Summary: portainer deploy tool for swarm
Home-page: UNKNOWN
Author: hsz
Author-email: hsz1273327@gmail.com
License: MIT License
Keywords: portainer,docker-compose,git
Platform: UNKNOWN
Classifier: License :: OSI Approved :: MIT License
Classifier: Programming Language :: Python :: 3.7
Classifier: Programming Language :: Python :: 3.8
Classifier: Programming Language :: Python :: 3.9
Requires-Dist: requests (>=2.25.1)
Requires-Dist: PyYaml (>=5.3.1)
Requires-Dist: schema-entry (>=0.1.5)
Requires-Dist: pyloggerhelper (>=0.0.3)
